{"v":"5.5.7","meta":{"g":"LottieFiles AE 0.1.21","a":"","k":"","d":"","tc":""},"fr":25,"ip":0,"op":101,"w":64,"h":64,"nm":"crop test","ddd":0,"assets":[{"id":"comp_0","layers":[{"ddd":0,"ind":1,"ty":4,"nm":"BLUE L WING Outlines","parent":3,"sr":1,"ks":{"o":{"a":0,"k":100,"ix":11},"r":{"a":0,"k":114.117,"ix":10},"p":{"a":0,"k":[156.818,129.668,0],"ix":2},"a":{"a":0,"k":[38.213,188.745,0],"ix":1},"s":{"a":0,"k":[-100,100,100],"ix":6}},"ao":0,"shapes":[{"ty":"gr","it":[{"ind":0,"ty":"sh","ix":1,"ks":{"a":0,"k":{"i":[[0,0],[-4.596,15.319],[1.532,19.915],[-9.192,-4.596],[0,-18.949],[0,0],[-9.192,-3.064],[4.596,-6.127],[-5.361,-14.553],[4.596,-3.064],[-2.609,-8.263],[0,0],[-9.192,-3.829],[25.3,5.06],[0,0],[0,0]],"o":[[0,0],[4.596,-15.319],[-1.532,-19.915],[9.191,4.596],[0,0],[0,0],[9.191,3.064],[-4.596,6.128],[2.996,8.132],[-4.596,3.064],[4.596,14.554],[0,0],[23.83,9.93],[-15.319,-3.063],[0,0],[0,0]],"v":[[-50.213,74.298],[-28.766,32.936],[-34.894,-49.787],[-27.234,-91.149],[-8.085,-53.617],[-8.085,-17.617],[23.319,-49.021],[4.936,-3.83],[34.808,-5.362],[0.34,32.936],[32.51,30.638],[3.404,62.043],[26.383,66.638],[17.957,84.255],[-24.17,86.553],[-28.766,95.745]],"c":false},"ix":2},"nm":"Path 1","mn":"ADBE Vector Shape - Group","hd":false},{"ty":"st","c":{"a":0,"k":[0,0,0,1],"ix":3},"o":{"a":0,"k":100,"ix":4},"w":{"a":0,"k":6,"ix":5},"lc":2,"lj":2,"bm":0,"nm":"Stroke 1","mn":"ADBE Vector Graphic - Stroke","hd":false},{"ty":"fl","c":{"a":0,"k":[0.952941179276,0.321568638086,0.647058844566,1],"ix":4},"o":{"a":0,"k":100,"ix":5},"r":1,"bm":0,"nm":"Fill 1","mn":"ADBE Vector Graphic - Fill","hd":false},{"ty":"tr","p":{"a":0,"k":[70.213,115.745],"ix":2},"a":{"a":0,"k":[0,0],"ix":1},"s":{"a":0,"k":[100,100],"ix":3},"r":{"a":0,"k":0,"ix":6},"o":{"a":0,"k":100,"ix":7},"sk":{"a":0,"k":0,"ix":4},"sa":{"a":0,"k":0,"ix":5},"nm":"Transform"}],"nm":"Group 1","np":3,"cix":2,"bm":0,"ix":1,"mn":"ADBE Vector Group","hd":false}],"ip":0,"op":103,"st":0,"bm":0},{"ddd":0,"ind":2,"ty":3,"nm":"Null 2","sr":1,"ks":{"o":{"a":0,"k":0,"ix":11},"r":{"a":0,"k":0,"ix":10},"p":{"a":0,"k":[1288,2182,0],"ix":2},"a":{"a":0,"k":[0,0,0],"ix":1},"s":{"a":0,"k":[384,384,100],"ix":6}},"ao":0,"ip":0,"op":200,"st":0,"bm":0},{"ddd":0,"ind":3,"ty":4,"nm":"BLUE TORSO Outlines","parent":2,"sr":1,"ks":{"o":{"a":0,"k":100,"ix":11},"r":{"a":0,"k":87.67,"ix":10},"p":{"a":1,"k":[{"i":{"x":0.833,"y":0.833},"o":{"x":0.167,"y":0.167},"t":0,"s":[-4.277,-41,0],"to":[0,0,0],"ti":[0,0,0]},{"i":{"x":0.833,"y":0.833},"o":{"x":0.167,"y":0.167},"t":12,"s":[-4.277,-41,0],"to":[0,0,0],"ti":[0,0,0]},{"i":{"x":0.833,"y":0.833},"o":{"x":0.167,"y":0.167},"t":18,"s":[-4.277,-41,0],"to":[0,0,0],"ti":[0,0,0]},{"i":{"x":0.833,"y":0.833},"o":{"x":0.167,"y":0.167},"t":55,"s":[-4.277,-41,0],"to":[0,0,0],"ti":[0,0,0]},{"i":{"x":0.833,"y":0.833},"o":{"x":0.167,"y":0.167},"t":59,"s":[-4.277,-41,0],"to":[0,0,0],"ti":[0,0,0]},{"t":63,"s":[-4.277,-41,0]}],"ix":2},"a":{"a":0,"k":[244.596,161.277,0],"ix":1},"s":{"a":0,"k":[100,100,100],"ix":6}},"ao":0,"shapes":[{"ty":"gr","it":[{"ty":"tr","p":{"a":0,"k":[168.595,117.277],"ix":2},"a":{"a":0,"k":[0,0],"ix":1},"s":{"a":0,"k":[100,100],"ix":3},"r":{"a":0,"k":0,"ix":6},"o":{"a":0,"k":100,"ix":7},"sk":{"a":0,"k":0,"ix":4},"sa":{"a":0,"k":0,"ix":5},"nm":"Transform"}],"nm":"Group 1","np":0,"cix":2,"bm":0,"ix":1,"mn":"ADBE Vector Group","hd":false},{"ty":"gr","it":[{"ind":0,"ty":"sh","ix":1,"ks":{"a":1,"k":[{"i":{"x":0.833,"y":0.833},"o":{"x":0.167,"y":0.167},"t":0,"s":[{"i":[[0,0],[-6.697,-2.395]],"o":[[0,0],[0,0]],"v":[[-37.175,103.181],[-24.682,113.101]],"c":false}]},{"i":{"x":0.833,"y":0.833},"o":{"x":0.167,"y":0.167},"t":12,"s":[{"i":[[0,0],[-6.697,-2.395]],"o":[[0,0],[0,0]],"v":[[-37.175,103.181],[-24.682,113.101]],"c":false}]},{"i":{"x":0.833,"y":0.833},"o":{"x":0.167,"y":0.167},"t":18,"s":[{"i":[[0,0],[-6.697,-2.395]],"o":[[0,0],[0,0]],"v":[[-26.896,121.114],[-14.402,131.033]],"c":false}]},{"i":{"x":0.833,"y":0.833},"o":{"x":0.167,"y":0.167},"t":19,"s":[{"i":[[0,0],[-8.837,-10.318]],"o":[[0,0],[0,0]],"v":[[-15.972,119.076],[-21.609,132.971]],"c":false}]},{"i":{"x":0.833,"y":0.833},"o":{"x":0.167,"y":0.167},"t":54,"s":[{"i":[[0,0],[-8.837,-10.318]],"o":[[0,0],[0,0]],"v":[[-15.972,119.076],[-21.609,132.971]],"c":false}]},{"i":{"x":0.833,"y":0.833},"o":{"x":0.167,"y":0.167},"t":55,"s":[{"i":[[0,0],[-6.697,-2.395]],"o":[[0,0],[0,0]],"v":[[-26.896,121.114],[-14.402,131.033]],"c":false}]},{"i":{"x":0.833,"y":0.833},"o":{"x":0.167,"y":0.167},"t":59,"s":[{"i":[[0,0],[-5.992,-3.831]],"o":[[0,0],[0,0]],"v":[[-39.294,86.978],[-29.333,99.439]],"c":false}]},{"t":63,"s":[{"i":[[0,0],[-6.697,-2.395]],"o":[[0,0],[0,0]],"v":[[-37.175,103.181],[-24.682,113.101]],"c":false}]}],"ix":2},"nm":"Path 1","mn":"ADBE Vector Shape - Group","hd":false},{"ty":"st","c":{"a":0,"k":[0,0,0,1],"ix":3},"o":{"a":0,"k":100,"ix":4},"w":{"a":0,"k":6,"ix":5},"lc":2,"lj":2,"bm":0,"nm":"Stroke 1","mn":"ADBE Vector Graphic - Stroke","hd":false},{"ty":"tr","p":{"a":0,"k":[48.596,51.149],"ix":2},"a":{"a":0,"k":[0,0],"ix":1},"s":{"a":0,"k":[100,100],"ix":3},"r":{"a":0,"k":0,"ix":6},"o":{"a":0,"k":100,"ix":7},"sk":{"a":0,"k":0,"ix":4},"sa":{"a":0,"k":0,"ix":5},"nm":"Transform"}],"nm":"Group 2","np":2,"cix":2,"bm":0,"ix":2,"mn":"ADBE Vector Group","hd":false},{"ty":"gr","it":[{"ind":0,"ty":"sh","ix":1,"ks":{"a":1,"k":[{"i":{"x":0.833,"y":0.833},"o":{"x":0.167,"y":0.167},"t":0,"s":[{"i":[[-1.35,7.694],[-17.064,-8.79],[7.403,-10.903],[3.041,1.928]],"o":[[1.35,-7.694],[17.064,8.79],[-7.403,10.902],[-8.284,-5.252]],"v":[[-49.087,101.939],[-22.442,83.939],[-7.933,114.243],[-29.119,125.472]],"c":true}]},{"i":{"x":0.833,"y":0.833},"o":{"x":0.167,"y":0.167},"t":12,"s":[{"i":[[-1.35,7.694],[-17.064,-8.79],[7.403,-10.903],[3.041,1.928]],"o":[[1.35,-7.694],[17.064,8.79],[-7.403,10.902],[-8.284,-5.252]],"v":[[-49.087,101.939],[-22.442,83.939],[-7.933,114.243],[-29.119,125.472]],"c":true}]},{"i":{"x":0.833,"y":0.833},"o":{"x":0.167,"y":0.167},"t":18,"s":[{"i":[[0.757,7.775],[-18.794,-3.905],[4.456,-12.402],[9.109,3.641]],"o":[[-0.757,-7.775],[18.794,3.905],[-3.504,9.751],[-9.108,-3.641]],"v":[[-40.848,125.364],[-19.989,100.893],[2.098,126.21],[-20.984,141.163]],"c":true}]},{"i":{"x":0.833,"y":0.833},"o":{"x":0.167,"y":0.167},"t":55,"s":[{"i":[[0.757,7.775],[-18.794,-3.905],[4.456,-12.402],[9.109,3.641]],"o":[[-0.757,-7.775],[18.794,3.905],[-3.504,9.751],[-9.108,-3.641]],"v":[[-40.848,125.364],[-19.989,100.893],[2.098,126.21],[-20.984,141.163]],"c":true}]},{"i":{"x":0.833,"y":0.833},"o":{"x":0.167,"y":0.167},"t":59,"s":[{"i":[[-3.035,7.198],[-14.669,-12.381],[9.652,-8.973],[6.277,7.538]],"o":[[3.035,-7.198],[14.669,12.381],[-9.651,8.972],[-6.276,-7.538]],"v":[[-51.762,82.919],[-21.769,71.329],[-14.844,102.266],[-41.53,105.466]],"c":true}]},{"t":63,"s":[{"i":[[-1.35,7.694],[-17.064,-8.79],[7.403,-10.903],[7.803,5.945]],"o":[[1.35,-7.694],[17.064,8.79],[-7.403,10.902],[-7.802,-5.945]],"v":[[-49.087,101.939],[-22.442,83.939],[-7.933,114.243],[-29.119,125.472]],"c":true}]}],"ix":2},"nm":"Path 1","mn":"ADBE Vector Shape - Group","hd":false},{"ty":"fl","c":{"a":0,"k":[1,1,1,1],"ix":4},"o":{"a":0,"k":100,"ix":5},"r":1,"bm":0,"nm":"Fill 1","mn":"ADBE Vector Graphic - Fill","hd":false},{"ty":"tr","p":{"a":0,"k":[48.34,56.255],"ix":2},"a":{"a":0,"k":[0,0],"ix":1},"s":{"a":0,"k":[100,100],"ix":3},"r":{"a":0,"k":0,"ix":6},"o":{"a":0,"k":100,"ix":7},"sk":{"a":0,"k":0,"ix":4},"sa":{"a":0,"k":0,"ix":5},"nm":"Transform"}],"nm":"Group 3","np":2,"cix":2,"bm":0,"ix":3,"mn":"ADBE Vector Group","hd":false},{"ty":"gr","it":[{"ind":0,"ty":"sh","ix":1,"ks":{"a":1,"k":[{"i":{"x":0.833,"y":0.833},"o":{"x":0.167,"y":0.167},"t":0,"s":[{"i":[[5.872,-10.865],[4.994,16.737],[-13.258,6.561],[-27.518,-2.963],[-16.826,7.404],[-4.595,-13.787],[35.234,-21.447],[33.702,9.191],[21.809,14.8],[13.639,-6.453]],"o":[[-5.872,10.865],[-4.994,-16.737],[22.351,-11.061],[12.892,1.388],[38.298,-16.851],[4.596,13.787],[-35.234,21.447],[-33.702,-9.192],[-19.005,-12.897],[-13.638,6.452]],"v":[[-136.044,64.192],[-172.342,32.943],[-150.996,-22.819],[-85.466,-22.274],[16.085,-26.809],[121.787,-25.276],[118.723,71.234],[17.617,88.085],[-47.988,62.593],[-103.443,65.656]],"c":true}]},{"i":{"x":0.833,"y":0.833},"o":{"x":0.167,"y":0.167},"t":12,"s":[{"i":[[5.872,-10.865],[4.994,16.737],[-13.258,6.561],[-27.518,-2.963],[-16.826,7.404],[-4.595,-13.787],[35.234,-21.447],[33.702,9.191],[21.809,14.8],[13.639,-6.453]],"o":[[-5.872,10.865],[-4.994,-16.737],[22.351,-11.061],[12.892,1.388],[38.298,-16.851],[4.596,13.787],[-35.234,21.447],[-33.702,-9.192],[-19.005,-12.897],[-13.638,6.452]],"v":[[-136.044,64.192],[-172.342,32.943],[-150.996,-22.819],[-85.466,-22.274],[16.085,-26.809],[121.787,-25.276],[118.723,71.234],[17.617,88.085],[-47.988,62.593],[-103.443,65.656]],"c":true}]},{"i":{"x":0.833,"y":0.833},"o":{"x":0.167,"y":0.167},"t":18,"s":[{"i":[[2.751,-12.04],[9.29,14.791],[-11.02,9.869],[-27.308,4.506],[-16.826,7.404],[-4.595,-13.787],[35.234,-21.447],[33.702,9.191],[21.809,14.8],[11.416,-9.866]],"o":[[-2.751,12.04],[-9.29,-14.791],[18.578,-16.637],[12.793,-2.111],[38.298,-16.851],[4.596,13.787],[-35.234,21.447],[-33.702,-9.192],[-19.005,-12.897],[-11.415,9.865]],"v":[[-122.597,79.296],[-165.932,58.895],[-160.281,-0.545],[-96.992,-17.549],[16.085,-26.809],[121.787,-25.276],[118.723,71.234],[17.617,88.085],[-47.988,62.593],[-90.793,71.986]],"c":true}]},{"i":{"x":0.833,"y":0.833},"o":{"x":0.167,"y":0.167},"t":55,"s":[{"i":[[2.751,-12.04],[9.29,14.791],[-11.02,9.869],[-27.308,4.506],[-16.826,7.404],[-4.595,-13.787],[35.234,-21.447],[33.702,9.191],[21.809,14.8],[11.416,-9.866]],"o":[[-2.751,12.04],[-9.29,-14.791],[18.578,-16.637],[12.793,-2.111],[38.298,-16.851],[4.596,13.787],[-35.234,21.447],[-33.702,-9.192],[-19.005,-12.897],[-11.415,9.865]],"v":[[-122.597,79.296],[-165.932,58.895],[-160.281,-0.545],[-96.992,-17.549],[16.085,-26.809],[121.787,-25.276],[118.723,71.234],[17.617,88.085],[-47.988,62.593],[-90.793,71.986]],"c":true}]},{"i":{"x":0.833,"y":0.833},"o":{"x":0.167,"y":0.167},"t":59,"s":[{"i":[[8.151,-9.278],[1.128,17.43],[-14.389,3.433],[-26.16,-9.037],[-16.826,7.404],[-4.595,-13.787],[35.234,-21.447],[33.702,9.191],[21.809,14.8],[14.736,-3.242]],"o":[[-8.151,9.278],[-1.128,-17.43],[24.258,-5.787],[12.256,4.234],[38.298,-16.851],[4.596,13.787],[-35.234,21.447],[-33.702,-9.192],[-19.005,-12.897],[-14.735,3.242]],"v":[[-144.626,50.827],[-173.024,12.257],[-139.757,-37.326],[-76.005,-22.15],[16.085,-26.809],[121.787,-25.276],[118.723,71.234],[17.617,88.085],[-47.988,62.593],[-113.177,59.539]],"c":true}]},{"t":63,"s":[{"i":[[5.872,-10.865],[4.994,16.737],[-13.258,6.561],[-27.518,-2.963],[-16.826,7.404],[-4.595,-13.787],[35.234,-21.447],[33.702,9.191],[21.809,14.8],[13.639,-6.453]],"o":[[-5.872,10.865],[-4.994,-16.737],[22.351,-11.061],[12.892,1.388],[38.298,-16.851],[4.596,13.787],[-35.234,21.447],[-33.702,-9.192],[-19.005,-12.897],[-13.638,6.452]],"v":[[-136.044,64.192],[-172.342,32.943],[-150.996,-22.819],[-85.466,-22.274],[16.085,-26.809],[121.787,-25.276],[118.723,71.234],[17.617,88.085],[-47.988,62.593],[-103.443,65.656]],"c":true}]}],"ix":2},"nm":"Path 1","mn":"ADBE Vector Shape - Group","hd":false},{"ty":"st","c":{"a":0,"k":[0,0,0,1],"ix":3},"o":{"a":0,"k":100,"ix":4},"w":{"a":0,"k":6,"ix":5},"lc":2,"lj":2,"bm":0,"nm":"Stroke 1","mn":"ADBE Vector Graphic - Stroke","hd":false},{"ty":"fl","c":{"a":0,"k":[0.954509794712,0.321164429188,0.649013638496,1],"ix":4},"o":{"a":0,"k":100,"ix":5},"r":1,"bm":0,"nm":"Fill 1","mn":"ADBE Vector Graphic - Fill","hd":false},{"ty":"tr","p":{"a":0,"k":[163.234,117.277],"ix":2},"a":{"a":0,"k":[0,0],"ix":1},"s":{"a":0,"k":[100,100],"ix":3},"r":{"a":0,"k":0,"ix":6},"o":{"a":0,"k":100,"ix":7},"sk":{"a":0,"k":0,"ix":4},"sa":{"a":0,"k":0,"ix":5},"nm":"Transform"}],"nm":"Group 4","np":3,"cix":2,"bm":0,"ix":4,"mn":"ADBE Vector Group","hd":false}],"ip":0,"op":103,"st":0,"bm":0},{"ddd":0,"ind":4,"ty":4,"nm":"BLUE L WING Outlines 2","parent":3,"sr":1,"ks":{"o":{"a":0,"k":100,"ix":11},"r":{"a":0,"k":115.741,"ix":10},"p":{"a":0,"k":[159.241,167.669,0],"ix":2},"a":{"a":0,"k":[38.213,188.745,0],"ix":1},"s":{"a":0,"k":[-100,100,100],"ix":6}},"ao":0,"shapes":[{"ty":"gr","it":[{"ind":0,"ty":"sh","ix":1,"ks":{"a":0,"k":{"i":[[0,0],[-4.596,15.319],[1.532,19.915],[-9.192,-4.596],[0,-18.949],[0,0],[-9.192,-3.064],[4.596,-6.127],[-5.361,-14.553],[4.596,-3.064],[-2.609,-8.263],[0,0],[-9.192,-3.829],[25.3,5.06],[0,0],[0,0]],"o":[[0,0],[4.596,-15.319],[-1.532,-19.915],[9.191,4.596],[0,0],[0,0],[9.191,3.064],[-4.596,6.128],[2.996,8.132],[-4.596,3.064],[4.596,14.554],[0,0],[23.83,9.93],[-15.319,-3.063],[0,0],[0,0]],"v":[[-50.213,74.298],[-28.766,32.936],[-34.894,-49.787],[-27.234,-91.149],[-8.085,-53.617],[-8.085,-17.617],[23.319,-49.021],[4.936,-3.83],[34.808,-5.362],[0.34,32.936],[32.51,30.638],[3.404,62.043],[26.383,66.638],[17.957,84.255],[-24.17,86.553],[-28.766,95.745]],"c":false},"ix":2},"nm":"Path 1","mn":"ADBE Vector Shape - Group","hd":false},{"ty":"st","c":{"a":0,"k":[0,0,0,1],"ix":3},"o":{"a":0,"k":100,"ix":4},"w":{"a":0,"k":8,"ix":5},"lc":2,"lj":2,"bm":0,"nm":"Stroke 1","mn":"ADBE Vector Graphic - Stroke","hd":false},{"ty":"fl","c":{"a":0,"k":[0.952941179276,0.321568638086,0.647058844566,1],"ix":4},"o":{"a":0,"k":100,"ix":5},"r":1,"bm":0,"nm":"Fill 1","mn":"ADBE Vector Graphic - Fill","hd":false},{"ty":"tr","p":{"a":0,"k":[70.213,115.745],"ix":2},"a":{"a":0,"k":[0,0],"ix":1},"s":{"a":0,"k":[100,100],"ix":3},"r":{"a":0,"k":0,"ix":6},"o":{"a":0,"k":100,"ix":7},"sk":{"a":0,"k":0,"ix":4},"sa":{"a":0,"k":0,"ix":5},"nm":"Transform"}],"nm":"Group 1","np":3,"cix":2,"bm":0,"ix":1,"mn":"ADBE Vector Group","hd":false}],"ip":0,"op":103,"st":0,"bm":0},{"ddd":0,"ind":5,"ty":4,"nm":"BLUE UPPER BEAK Outlines","parent":3,"sr":1,"ks":{"o":{"a":0,"k":100,"ix":11},"r":{"a":1,"k":[{"i":{"x":[0.833],"y":[0.833]},"o":{"x":[0.167],"y":[0.167]},"t":0,"s":[-76.305]},{"i":{"x":[0.833],"y":[0.833]},"o":{"x":[0.167],"y":[0.167]},"t":12,"s":[-76.305]},{"i":{"x":[0.833],"y":[0.833]},"o":{"x":[0.167],"y":[0.167]},"t":18,"s":[-88.761]},{"i":{"x":[0.833],"y":[0.833]},"o":{"x":[0.167],"y":[0.167]},"t":23,"s":[-93.487]},{"i":{"x":[0.833],"y":[0.833]},"o":{"x":[0.167],"y":[0.167]},"t":28,"s":[-84.906]},{"i":{"x":[0.833],"y":[0.833]},"o":{"x":[0.167],"y":[0.167]},"t":32,"s":[-92.336]},{"i":{"x":[0.833],"y":[0.833]},"o":{"x":[0.167],"y":[0.167]},"t":40,"s":[-76.305]},{"i":{"x":[0.833],"y":[0.833]},"o":{"x":[0.167],"y":[0.167]},"t":46,"s":[-83.77]},{"i":{"x":[0.833],"y":[0.833]},"o":{"x":[0.167],"y":[0.167]},"t":55,"s":[-85.48]},{"i":{"x":[0.833],"y":[0.833]},"o":{"x":[0.167],"y":[0.167]},"t":59,"s":[-62.78]},{"t":63,"s":[-76.305]}],"ix":10},"p":{"a":1,"k":[{"i":{"x":0.833,"y":0.833},"o":{"x":0.167,"y":0.167},"t":0,"s":[39.67,190.9,0],"to":[0,0,0],"ti":[0,0,0]},{"i":{"x":0.833,"y":0.833},"o":{"x":0.167,"y":0.167},"t":12,"s":[39.67,190.9,0],"to":[0.992,0.207,0],"ti":[-0.992,-0.207,0]},{"i":{"x":0.833,"y":0.833},"o":{"x":0.167,"y":0.167},"t":18,"s":[45.625,192.144,0],"to":[0,0,0],"ti":[0,0,0]},{"i":{"x":0.833,"y":0.833},"o":{"x":0.167,"y":0.167},"t":55,"s":[45.625,192.144,0],"to":[-3.472,-2.81,0],"ti":[0.992,0.207,0]},{"i":{"x":0.833,"y":0.833},"o":{"x":0.167,"y":0.167},"t":59,"s":[24.793,175.283,0],"to":[-0.992,-0.207,0],"ti":[-2.48,-2.603,0]},{"t":63,"s":[39.67,190.9,0]}],"ix":2},"a":{"a":0,"k":[117.809,53.277,0],"ix":1},"s":{"a":0,"k":[100,100,100],"ix":6}},"ao":0,"shapes":[{"ty":"gr","it":[{"ind":0,"ty":"sh","ix":1,"ks":{"a":1,"k":[{"i":{"x":0.833,"y":0.833},"o":{"x":0.167,"y":0.167},"t":0,"s":[{"i":[[0,0],[9.192,1.532],[0,0],[-12.255,0],[0,0]],"o":[[0,0],[-9.191,-1.532],[0,0],[12.256,0],[0,0]],"v":[[26.553,-4.341],[1.021,0.766],[-33.29,0.596],[5.106,6.893],[31.149,3.32]],"c":true}]},{"i":{"x":0.833,"y":0.833},"o":{"x":0.167,"y":0.167},"t":12,"s":[{"i":[[0,0],[9.192,1.532],[0,0],[-12.255,0],[0,0]],"o":[[0,0],[-9.191,-1.532],[0,0],[12.256,0],[0,0]],"v":[[26.553,-4.341],[1.021,0.766],[-33.29,0.596],[5.106,6.893],[31.149,3.32]],"c":true}]},{"i":{"x":0.833,"y":0.833},"o":{"x":0.167,"y":0.167},"t":18,"s":[{"i":[[0,0],[10.871,-2.392],[0,0],[-11.864,3.073],[0,0]],"o":[[0,0],[-9.1,2.003],[0,0],[12.964,-3.357],[0,0]],"v":[[16.469,-0.032],[-1.643,4.417],[-33.892,20.746],[5.676,10.063],[17.094,6.052]],"c":true}]},{"i":{"x":0.833,"y":0.833},"o":{"x":0.167,"y":0.167},"t":55,"s":[{"i":[[0,0],[10.871,-2.392],[0,0],[-11.864,3.073],[0,0]],"o":[[0,0],[-9.1,2.003],[0,0],[12.964,-3.357],[0,0]],"v":[[16.469,-0.032],[-1.643,4.417],[-33.892,20.746],[5.676,10.063],[17.094,6.052]],"c":true}]},{"i":{"x":0.833,"y":0.833},"o":{"x":0.167,"y":0.167},"t":59,"s":[{"i":[[0,0],[10.871,-2.392],[0,0],[-11.864,3.073],[0,0]],"o":[[0,0],[-9.1,2.003],[0,0],[12.964,-3.357],[0,0]],"v":[[16.469,-0.032],[-1.643,4.417],[-33.892,20.746],[5.676,10.063],[17.094,6.052]],"c":true}]},{"t":63,"s":[{"i":[[0,0],[9.192,1.532],[0,0],[-12.255,0],[0,0]],"o":[[0,0],[-9.191,-1.532],[0,0],[12.256,0],[0,0]],"v":[[26.553,-4.341],[1.021,0.766],[-33.29,0.596],[5.106,6.893],[31.149,3.32]],"c":true}]}],"ix":2},"nm":"Path 1","mn":"ADBE Vector Shape - Group","hd":false},{"ty":"fl","c":{"a":0,"k":[1,1,1,1],"ix":4},"o":{"a":0,"k":100,"ix":5},"r":1,"bm":0,"nm":"Fill 1","mn":"ADBE Vector Graphic - Fill","hd":false},{"ty":"tr","p":{"a":0,"k":[84.341,48.34],"ix":2},"a":{"a":0,"k":[0,0],"ix":1},"s":{"a":0,"k":[100,100],"ix":3},"r":{"a":0,"k":0,"ix":6},"o":{"a":0,"k":100,"ix":7},"sk":{"a":0,"k":0,"ix":4},"sa":{"a":0,"k":0,"ix":5},"nm":"Transform"}],"nm":"Group 1","np":2,"cix":2,"bm":0,"ix":1,"mn":"ADBE Vector Group","hd":false},{"ty":"gr","it":[{"ind":0,"ty":"sh","ix":1,"ks":{"a":1,"k":[{"i":{"x":0.833,"y":0.833},"o":{"x":0.167,"y":0.167},"t":0,"s":[{"i":[[-12.255,9.192],[1.532,6.128],[17.177,3.164],[0,0],[-26.917,-5.141],[0,0]],"o":[[12.255,-9.191],[-1.532,-6.128],[-19.404,-3.575],[0,0],[26.917,5.141],[0,0]],"v":[[50.554,12.51],[33.702,-8.425],[-1.531,-3.83],[-69.525,-7.971],[-23.743,18.908],[35.235,23.744]],"c":true}]},{"i":{"x":0.833,"y":0.833},"o":{"x":0.167,"y":0.167},"t":12,"s":[{"i":[[-12.255,9.192],[1.532,6.128],[17.177,3.164],[0,0],[-26.917,-5.141],[0,0]],"o":[[12.255,-9.191],[-1.532,-6.128],[-19.404,-3.575],[0,0],[26.917,5.141],[0,0]],"v":[[50.554,12.51],[33.702,-8.425],[-1.531,-3.83],[-69.525,-7.971],[-23.743,18.908],[35.235,23.744]],"c":true}]},{"i":{"x":0.833,"y":0.833},"o":{"x":0.167,"y":0.167},"t":18,"s":[{"i":[[-12.255,9.192],[1.532,6.128],[16.074,-6.833],[0,0],[-27.083,4.179],[0,0]],"o":[[12.255,-9.191],[-1.532,-6.128],[-29.587,12.577],[0,0],[27.083,-4.179],[0,0]],"v":[[50.554,12.51],[33.702,-8.425],[-5.363,3.143],[-64.052,36.662],[-15.18,34.575],[43.6,30.905]],"c":true}]},{"i":{"x":0.833,"y":0.833},"o":{"x":0.167,"y":0.167},"t":55,"s":[{"i":[[-12.255,9.192],[1.532,6.128],[16.074,-6.833],[0,0],[-27.083,4.179],[0,0]],"o":[[12.255,-9.191],[-1.532,-6.128],[-29.587,12.577],[0,0],[27.083,-4.179],[0,0]],"v":[[50.554,12.51],[33.702,-8.425],[-5.363,3.143],[-64.052,36.662],[-15.18,34.575],[43.6,30.905]],"c":true}]},{"i":{"x":0.833,"y":0.833},"o":{"x":0.167,"y":0.167},"t":59,"s":[{"i":[[-12.255,9.192],[1.532,6.128],[16.074,-6.833],[0,0],[-27.083,4.179],[0,0]],"o":[[12.255,-9.191],[-1.532,-6.128],[-29.587,12.577],[0,0],[27.083,-4.179],[0,0]],"v":[[50.554,12.51],[33.702,-8.425],[-5.363,3.143],[-64.052,36.662],[-15.18,34.575],[43.6,30.905]],"c":true}]},{"t":63,"s":[{"i":[[-12.255,9.192],[1.532,6.128],[17.177,3.164],[0,0],[-26.917,-5.141],[0,0]],"o":[[12.255,-9.191],[-1.532,-6.128],[-19.404,-3.575],[0,0],[26.917,5.141],[0,0]],"v":[[50.554,12.51],[33.702,-8.425],[-1.531,-3.83],[-69.525,-7.971],[-23.743,18.908],[35.235,23.744]],"c":true}]}],"ix":2},"nm":"Path 1","mn":"ADBE Vector Shape - Group","hd":false},{"ty":"st","c":{"a":0,"k":[0,0,0,1],"ix":3},"o":{"a":0,"k":100,"ix":4},"w":{"a":0,"k":6,"ix":5},"lc":2,"lj":2,"bm":0,"nm":"Stroke 1","mn":"ADBE Vector Graphic - Stroke","hd":false},{"ty":"fl","c":{"a":0,"k":[1,0.674509803922,0.450980422076,1],"ix":4},"o":{"a":0,"k":100,"ix":5},"r":1,"bm":0,"nm":"Fill 1","mn":"ADBE Vector Graphic - Fill","hd":false},{"ty":"tr","p":{"a":0,"k":[82.809,45.277],"ix":2},"a":{"a":0,"k":[0,0],"ix":1},"s":{"a":0,"k":[100,100],"ix":3},"r":{"a":0,"k":0,"ix":6},"o":{"a":0,"k":100,"ix":7},"sk":{"a":0,"k":0,"ix":4},"sa":{"a":0,"k":0,"ix":5},"nm":"Transform"}],"nm":"Group 2","np":3,"cix":2,"bm":0,"ix":2,"mn":"ADBE Vector Group","hd":false}],"ip":0,"op":103,"st":0,"bm":0},{"ddd":0,"ind":6,"ty":4,"nm":"BLUE LOWER BEAK Outlines","parent":3,"sr":1,"ks":{"o":{"a":0,"k":100,"ix":11},"r":{"a":1,"k":[{"i":{"x":[0.833],"y":[0.833]},"o":{"x":[0.167],"y":[0.167]},"t":0,"s":[-45.332]},{"i":{"x":[0.833],"y":[0.833]},"o":{"x":[0.167],"y":[0.167]},"t":12,"s":[-45.332]},{"i":{"x":[0.833],"y":[0.833]},"o":{"x":[0.167],"y":[0.167]},"t":18,"s":[-90.276]},{"i":{"x":[0.833],"y":[0.833]},"o":{"x":[0.167],"y":[0.167]},"t":23,"s":[-75.805]},{"i":{"x":[0.833],"y":[0.833]},"o":{"x":[0.167],"y":[0.167]},"t":28,"s":[-81.491]},{"i":{"x":[0.833],"y":[0.833]},"o":{"x":[0.167],"y":[0.167]},"t":32,"s":[-76.246]},{"i":{"x":[0.833],"y":[0.833]},"o":{"x":[0.167],"y":[0.167]},"t":40,"s":[-90.276]},{"i":{"x":[0.833],"y":[0.833]},"o":{"x":[0.167],"y":[0.167]},"t":46,"s":[-70.743]},{"i":{"x":[0.833],"y":[0.833]},"o":{"x":[0.167],"y":[0.167]},"t":55,"s":[-70.743]},{"i":{"x":[0.833],"y":[0.833]},"o":{"x":[0.167],"y":[0.167]},"t":59,"s":[-43.965]},{"t":63,"s":[-45.332]}],"ix":10},"p":{"a":1,"k":[{"i":{"x":0.833,"y":0.833},"o":{"x":0.167,"y":0.167},"t":0,"s":[56.191,180.576,0],"to":[0,0,0],"ti":[0,0,0]},{"i":{"x":0.833,"y":0.833},"o":{"x":0.167,"y":0.167},"t":12,"s":[56.191,180.576,0],"to":[0.54,-0.979,0],"ti":[-0.54,0.979,0]},{"i":{"x":0.833,"y":0.833},"o":{"x":0.167,"y":0.167},"t":18,"s":[59.433,174.703,0],"to":[0,0,0],"ti":[0,0,0]},{"i":{"x":0.833,"y":0.833},"o":{"x":0.167,"y":0.167},"t":55,"s":[59.433,174.703,0],"to":[-2.296,1.074,0],"ti":[0.54,-0.979,0]},{"i":{"x":0.833,"y":0.833},"o":{"x":0.167,"y":0.167},"t":59,"s":[45.659,181.148,0],"to":[-0.54,0.979,0],"ti":[-1.755,0.095,0]},{"t":63,"s":[56.191,180.576,0]}],"ix":2},"a":{"a":0,"k":[132.149,48.744,0],"ix":1},"s":{"a":0,"k":[100,100,100],"ix":6}},"ao":0,"shapes":[{"ty":"gr","it":[{"ind":0,"ty":"sh","ix":1,"ks":{"a":1,"k":[{"i":{"x":0.833,"y":0.833},"o":{"x":0.167,"y":0.167},"t":0,"s":[{"i":[[-6.128,-12.255],[4.34,-2.043],[25.044,-5.677],[6.081,-0.749],[-23.204,12.118],[0,0]],"o":[[4.988,9.975],[-4.341,2.042],[-33.571,7.61],[-6.082,0.749],[23.204,-12.118],[0,0]],"v":[[55.532,-23.49],[59.799,6.302],[8.114,34.035],[-56.96,34.762],[-8.47,14.901],[26.17,-28.596]],"c":true}]},{"i":{"x":0.833,"y":0.833},"o":{"x":0.167,"y":0.167},"t":12,"s":[{"i":[[-6.128,-12.255],[4.34,-2.043],[25.044,-5.677],[6.081,-0.749],[-23.204,12.118],[0,0]],"o":[[4.988,9.975],[-4.341,2.042],[-33.571,7.61],[-6.082,0.749],[23.204,-12.118],[0,0]],"v":[[55.532,-23.49],[59.799,6.302],[8.114,34.035],[-56.96,34.762],[-8.47,14.901],[26.17,-28.596]],"c":true}]},{"i":{"x":0.833,"y":0.833},"o":{"x":0.167,"y":0.167},"t":18,"s":[{"i":[[-6.128,-12.255],[4.34,-2.043],[24.511,-7.659],[6.127,0],[-20.695,16.031],[0,0]],"o":[[4.988,9.975],[-4.341,2.042],[-24.51,7.66],[-6.128,0],[21.658,-16.777],[0,0]],"v":[[55.532,-23.49],[59.716,0.825],[4.723,28.085],[-37.654,37.794],[-2.22,4.299],[31.823,-20.83]],"c":true}]},{"i":{"x":0.833,"y":0.833},"o":{"x":0.167,"y":0.167},"t":55,"s":[{"i":[[-6.128,-12.255],[4.34,-2.043],[24.511,-7.659],[6.127,0],[-20.695,16.031],[0,0]],"o":[[4.988,9.975],[-4.341,2.042],[-24.51,7.66],[-6.128,0],[21.658,-16.777],[0,0]],"v":[[55.532,-23.49],[59.716,0.825],[4.723,28.085],[-37.654,37.794],[-2.22,4.299],[31.823,-20.83]],"c":true}]},{"i":{"x":0.833,"y":0.833},"o":{"x":0.167,"y":0.167},"t":59,"s":[{"i":[[-6.128,-12.255],[4.34,-2.043],[24.511,-7.659],[6.127,0],[-20.695,16.031],[0,0]],"o":[[4.988,9.975],[-4.341,2.042],[-24.51,7.66],[-6.128,0],[21.658,-16.777],[0,0]],"v":[[55.532,-23.49],[59.716,0.825],[4.723,28.085],[-37.654,37.794],[-2.22,4.299],[31.823,-20.83]],"c":true}]},{"t":63,"s":[{"i":[[-6.128,-12.255],[4.34,-2.043],[25.044,-5.677],[6.081,-0.749],[-23.204,12.118],[0,0]],"o":[[4.988,9.975],[-4.341,2.042],[-33.571,7.61],[-6.082,0.749],[23.204,-12.118],[0,0]],"v":[[55.532,-23.49],[59.799,6.302],[8.114,34.035],[-56.96,34.762],[-8.47,14.901],[26.17,-28.596]],"c":true}]}],"ix":2},"nm":"Path 1","mn":"ADBE Vector Shape - Group","hd":false},{"ty":"st","c":{"a":0,"k":[0,0,0,1],"ix":3},"o":{"a":0,"k":100,"ix":4},"w":{"a":0,"k":6,"ix":5},"lc":2,"lj":2,"bm":0,"nm":"Stroke 1","mn":"ADBE Vector Graphic - Stroke","hd":false},{"ty":"fl","c":{"a":0,"k":[1,0.674509803922,0.450980422076,1],"ix":4},"o":{"a":0,"k":100,"ix":5},"r":1,"bm":0,"nm":"Fill 1","mn":"ADBE Vector Graphic - Fill","hd":false},{"ty":"tr","p":{"a":0,"k":[81.149,55.745],"ix":2},"a":{"a":0,"k":[0,0],"ix":1},"s":{"a":0,"k":[100,100],"ix":3},"r":{"a":0,"k":0,"ix":6},"o":{"a":0,"k":100,"ix":7},"sk":{"a":0,"k":0,"ix":4},"sa":{"a":0,"k":0,"ix":5},"nm":"Transform"}],"nm":"Group 1","np":3,"cix":2,"bm":0,"ix":1,"mn":"ADBE Vector Group","hd":false}],"ip":0,"op":103,"st":0,"bm":0},{"ddd":0,"ind":7,"ty":4,"nm":"BLUE L LEG Outlines","parent":2,"sr":1,"ks":{"o":{"a":0,"k":100,"ix":11},"r":{"a":0,"k":80.889,"ix":10},"p":{"a":0,"k":[36.101,-6.483,0],"ix":2},"a":{"a":0,"k":[21.42,20.187,0],"ix":1},"s":{"a":0,"k":[100,100,100],"ix":6}},"ao":0,"shapes":[{"ty":"gr","it":[{"ind":0,"ty":"sh","ix":1,"ks":{"a":0,"k":{"i":[[0,0],[-22.529,-2.011],[0,0],[-4.836,-9.933]],"o":[[0,0],[25.482,2.275],[0,0],[0,0]],"v":[[-56.079,-40.203],[14.887,-15.8],[85.578,-37.305],[86.423,-9.363]],"c":false},"ix":2},"nm":"Path 1","mn":"ADBE Vector Shape - Group","hd":false},{"ty":"st","c":{"a":0,"k":[0,0,0,1],"ix":3},"o":{"a":0,"k":100,"ix":4},"w":{"a":0,"k":8,"ix":5},"lc":2,"lj":2,"bm":0,"nm":"Stroke 1","mn":"ADBE Vector Graphic - Stroke","hd":false},{"ty":"tr","p":{"a":0,"k":[67.489,59.83],"ix":2},"a":{"a":0,"k":[0,0],"ix":1},"s":{"a":0,"k":[100,100],"ix":3},"r":{"a":0,"k":0,"ix":6},"o":{"a":0,"k":100,"ix":7},"sk":{"a":0,"k":0,"ix":4},"sa":{"a":0,"k":0,"ix":5},"nm":"Transform"}],"nm":"Group 1","np":2,"cix":2,"bm":0,"ix":1,"mn":"ADBE Vector Group","hd":false}],"ip":0,"op":103,"st":0,"bm":0},{"ddd":0,"ind":8,"ty":4,"nm":"BLUE R LEG Outlines","parent":2,"sr":1,"ks":{"o":{"a":0,"k":100,"ix":11},"r":{"a":0,"k":2.647,"ix":10},"p":{"a":0,"k":[-5.253,0.106,0],"ix":2},"a":{"a":0,"k":[51.277,26.234,0],"ix":1},"s":{"a":0,"k":[100,100,100],"ix":6}},"ao":0,"shapes":[{"ty":"gr","it":[{"ind":0,"ty":"sh","ix":1,"ks":{"a":0,"k":{"i":[[0,0],[-6.128,-26.042],[0,0],[0,0]],"o":[[0,0],[6.127,26.043],[0,0],[0,0]],"v":[[0.686,-66.73],[-4.932,-4.078],[26.164,61.411],[-1.653,68.802]],"c":false},"ix":2},"nm":"Path 1","mn":"ADBE Vector Shape - Group","hd":false},{"ty":"st","c":{"a":0,"k":[0,0,0,1],"ix":3},"o":{"a":0,"k":100,"ix":4},"w":{"a":0,"k":8,"ix":5},"lc":2,"lj":2,"bm":0,"nm":"Stroke 1","mn":"ADBE Vector Graphic - Stroke","hd":false},{"ty":"tr","p":{"a":0,"k":[45.276,91.234],"ix":2},"a":{"a":0,"k":[0,0],"ix":1},"s":{"a":0,"k":[100,100],"ix":3},"r":{"a":0,"k":0,"ix":6},"o":{"a":0,"k":100,"ix":7},"sk":{"a":0,"k":0,"ix":4},"sa":{"a":0,"k":0,"ix":5},"nm":"Transform"}],"nm":"Group 1","np":2,"cix":2,"bm":0,"ix":1,"mn":"ADBE Vector Group","hd":false}],"ip":0,"op":103,"st":0,"bm":0},{"ddd":0,"ind":9,"ty":4,"nm":"BLUE TAIL Outlines","parent":3,"sr":1,"ks":{"o":{"a":0,"k":100,"ix":11},"r":{"a":0,"k":39.909,"ix":10},"p":{"a":0,"k":[251.702,103.574,0],"ix":2},"a":{"a":0,"k":[70.937,128.085,0],"ix":1},"s":{"a":0,"k":[100,100,100],"ix":6}},"ao":0,"shapes":[{"ty":"gr","it":[{"ind":0,"ty":"sh","ix":1,"ks":{"a":0,"k":{"i":[[0,0],[-3.146,12.234],[4.596,6.127],[4.596,-12.255],[0,0],[14.553,5.362],[1.532,-12.255],[0,0],[9.191,7.66],[-1.532,-13.788],[0,0],[9.191,-1.532],[-3.064,-12.255],[-7.659,-7.66],[0,0]],"o":[[0,0],[6.894,-26.809],[-4.596,-6.128],[-4.596,12.255],[0,0],[-6.098,-2.246],[-1.532,12.255],[0,0],[-9.192,-7.659],[1.532,13.787],[0,0],[-9.192,1.532],[3.064,12.256],[7.66,7.659],[0,0]],"v":[[26.426,52.085],[44.042,19.149],[40.978,-45.957],[23.361,-17.617],[16.469,15.319],[5.745,-43.66],[-6.51,-19.915],[-4.979,13.787],[-23.362,-24.511],[-31.022,-12.255],[-21.829,21.447],[-41.745,-6.128],[-46.341,12.255],[-32.553,36.766],[-9.574,50.553]],"c":false},"ix":2},"nm":"Path 1","mn":"ADBE Vector Shape - Group","hd":false},{"ty":"st","c":{"a":0,"k":[0,0,0,1],"ix":3},"o":{"a":0,"k":100,"ix":4},"w":{"a":0,"k":8,"ix":5},"lc":2,"lj":2,"bm":0,"nm":"Stroke 1","mn":"ADBE Vector Graphic - Stroke","hd":false},{"ty":"fl","c":{"a":0,"k":[0.952941179276,0.321568638086,0.647058844566,1],"ix":4},"o":{"a":0,"k":100,"ix":5},"r":1,"bm":0,"nm":"Fill 1","mn":"ADBE Vector Graphic - Fill","hd":false},{"ty":"tr","p":{"a":0,"k":[70.937,72.085],"ix":2},"a":{"a":0,"k":[0,0],"ix":1},"s":{"a":0,"k":[100,100],"ix":3},"r":{"a":0,"k":0,"ix":6},"o":{"a":0,"k":100,"ix":7},"sk":{"a":0,"k":0,"ix":4},"sa":{"a":0,"k":0,"ix":5},"nm":"Transform"}],"nm":"Group 1","np":3,"cix":2,"bm":0,"ix":1,"mn":"ADBE Vector Group","hd":false}],"ip":0,"op":103,"st":0,"bm":0},{"ddd":0,"ind":10,"ty":4,"nm":"BALL DRIPS Outlines","parent":2,"sr":1,"ks":{"o":{"a":0,"k":100,"ix":11},"r":{"a":0,"k":0,"ix":10},"p":{"a":0,"k":[29.599,133.404,0],"ix":2},"a":{"a":0,"k":[1004.634,382.997,0],"ix":1},"s":{"a":0,"k":[48.849,45.902,100],"ix":6}},"ao":0,"shapes":[{"ty":"gr","it":[{"d":1,"ty":"el","s":{"a":0,"k":[668.852,137.705],"ix":2},"p":{"a":0,"k":[0,0],"ix":3},"nm":"Ellipse Path 1","mn":"ADBE Vector Shape - Ellipse","hd":false},{"ty":"st","c":{"a":0,"k":[1,1,1,1],"ix":3},"o":{"a":0,"k":100,"ix":4},"w":{"a":0,"k":0,"ix":5},"lc":1,"lj":1,"ml":4,"bm":0,"nm":"Stroke 1","mn":"ADBE Vector Graphic - Stroke","hd":false},{"ty":"fl","c":{"a":0,"k":[0,0,0,1],"ix":4},"o":{"a":0,"k":20,"ix":5},"r":1,"bm":0,"nm":"Fill 1","mn":"ADBE Vector Graphic - Fill","hd":false},{"ty":"tr","p":{"a":0,"k":[1017.4,379.927],"ix":2},"a":{"a":0,"k":[0,0],"ix":1},"s":{"a":0,"k":[100,100],"ix":3},"r":{"a":0,"k":0,"ix":6},"o":{"a":0,"k":100,"ix":7},"sk":{"a":0,"k":0,"ix":4},"sa":{"a":0,"k":0,"ix":5},"nm":"Transform"}],"nm":"Ellipse 1","np":3,"cix":2,"bm":0,"ix":1,"mn":"ADBE Vector Group","hd":false}],"ip":0,"op":298,"st":-177,"bm":0}]}],"layers":[{"ddd":0,"ind":8,"ty":0,"nm":"AVATAR - Lemmenjoki","refId":"comp_0","sr":1,"ks":{"o":{"a":0,"k":100,"ix":11},"r":{"a":0,"k":0,"ix":10},"p":{"a":0,"k":[32,32,0],"ix":2},"a":{"a":0,"k":[1200,1200,0],"ix":1},"s":{"a":0,"k":[5.5,5.5,100],"ix":6}},"ao":0,"hasMask":true,"masksProperties":[{"inv":false,"mode":"a","pt":{"a":0,"k":{"i":[[322.584,0],[0,-322.585],[-322.585,0],[0,322.584]],"o":[[-322.585,0],[0,322.584],[322.584,0],[0,-322.585]],"v":[[1206.818,627.273],[622.727,1211.364],[1206.818,1795.455],[1790.909,1211.364]],"c":true},"ix":1},"o":{"a":0,"k":100,"ix":3},"x":{"a":0,"k":0,"ix":4},"nm":"Mask 1"}],"w":2400,"h":2400,"ip":0,"op":200,"st":0,"bm":0}],"markers":[]}